safetensors_mlir/.safetensors_mlir_gml_libs/libexternal_Sabseil-cpp~_Sabsl_Sbase_Slibbase.so
safetensors_mlir/.safetensors_mlir_gml_libs/libexternal_Sabseil-cpp~_Sabsl_Sbase_Sliblog_Useverity.so
safetensors_mlir/.safetensors_mlir_gml_libs/libexternal_Sabseil-cpp~_Sabsl_Sbase_Slibmalloc_Uinternal.so
safetensors_mlir/.safetensors_mlir_gml_libs/libexternal_Sabseil-cpp~_Sabsl_Sbase_Slibraw_Ulogging_Uinternal.so
safetensors_mlir/.safetensors_mlir_gml_libs/libexternal_Sabseil-cpp~_Sabsl_Sbase_Slibspinlock_Uwait.so
safetensors_mlir/.safetensors_mlir_gml_libs/libexternal_Sabseil-cpp~_Sabsl_Sbase_Slibstrerror.so
safetensors_mlir/.safetensors_mlir_gml_libs/libexternal_Sabseil-cpp~_Sabsl_Sbase_Slibthrow_Udelegate.so
safetensors_mlir/.safetensors_mlir_gml_libs/libexternal_Sabseil-cpp~_Sabsl_Scontainer_Slibhashtablez_Usampler.so
safetensors_mlir/.safetensors_mlir_gml_libs/libexternal_Sabseil-cpp~_Sabsl_Scontainer_Slibraw_Uhash_Uset.so
safetensors_mlir/.safetensors_mlir_gml_libs/libexternal_Sabseil-cpp~_Sabsl_Scrc_Slibcpu_Udetect.so
safetensors_mlir/.safetensors_mlir_gml_libs/libexternal_Sabseil-cpp~_Sabsl_Scrc_Slibcrc32c.so
safetensors_mlir/.safetensors_mlir_gml_libs/libexternal_Sabseil-cpp~_Sabsl_Scrc_Slibcrc_Ucord_Ustate.so
safetensors_mlir/.safetensors_mlir_gml_libs/libexternal_Sabseil-cpp~_Sabsl_Scrc_Slibcrc_Uinternal.so
safetensors_mlir/.safetensors_mlir_gml_libs/libexternal_Sabseil-cpp~_Sabsl_Sdebugging_Slibdebugging_Uinternal.so
safetensors_mlir/.safetensors_mlir_gml_libs/libexternal_Sabseil-cpp~_Sabsl_Sdebugging_Slibdemangle_Uinternal.so
safetensors_mlir/.safetensors_mlir_gml_libs/libexternal_Sabseil-cpp~_Sabsl_Sdebugging_Slibexamine_Ustack.so
safetensors_mlir/.safetensors_mlir_gml_libs/libexternal_Sabseil-cpp~_Sabsl_Sdebugging_Slibfailure_Usignal_Uhandler.so
safetensors_mlir/.safetensors_mlir_gml_libs/libexternal_Sabseil-cpp~_Sabsl_Sdebugging_Slibstacktrace.so
safetensors_mlir/.safetensors_mlir_gml_libs/libexternal_Sabseil-cpp~_Sabsl_Sdebugging_Slibsymbolize.so
safetensors_mlir-0.0.3.dist-info/WHEEL
safetensors_mlir-0.0.3.dist-info/METADATA
safetensors_mlir-0.0.3.dist-info/RECORD
