Metadata-Version: 2.1
Name: safetensors-mlir
Author: Gimlet Labs, Inc.
Author-email: support@gimletlabs.ai
Classifier: Programming Language :: Python :: 3
Classifier: Operating System :: OS Independent
Classifier: License :: OSI Approved :: Apache Software License
Classifier: Typing :: Typed
Requires-Python: >=3
Requires-Dist: mlir-gml
Version: 0.0.3
